enlil/__init__.py
enlil/cli.py
enlil/management.py
enlil/settings.py
enlil/scaffolds/app/__init__.py
enlil/scaffolds/app/models.py
enlil/scaffolds/app/routers.py
enlil/scaffolds/app/utils.py
enlil/scaffolds/app/serializers/data_objects.py
enlil/scaffolds/app/serializers/input.py
enlil/scaffolds/app/serializers/output.py
enlil/scaffolds/app/services/base.py
enlil/scaffolds/app/tests/conftest.py
enlil/scaffolds/app/views/api.py
enlil/scaffolds/app/views/ui.py
enlil/scaffolds/crud/factory/template.py
enlil/scaffolds/crud/model/template.py
enlil/scaffolds/crud/serializer/input.py
enlil/scaffolds/crud/serializer/output.py
enlil/scaffolds/crud/service/template.py
enlil/scaffolds/crud/test/template.py
enlil/scaffolds/crud/view/template.py
enlil/scaffolds/project/manage.py
enlil/scaffolds/project/pytest.ini
enlil/scaffolds/project/src/__init__.py
enlil/scaffolds/project/src/config.py
enlil/scaffolds/project/src/conftest.py
enlil/scaffolds/project/src/main.py
enlil/scaffolds/project/src/apps/__init__.py
enlil/scaffolds/project/src/core/__init__.py
enlil/scaffolds/project/src/core/containers.py
enlil/scaffolds/project/src/core/database.py
enlil/scaffolds/project/src/core/dependencies.py
enlil/scaffolds/project/src/core/exceptions.py
enlil/scaffolds/project/src/core/models.py
enlil/scaffolds/project/src/core/services.py
enlil/scaffolds/project/src/templates/base.html
enlil/scaffolds/project/src/templates/index.html
enlil_framework-0.1.1.dist-info/METADATA
enlil_framework-0.1.1.dist-info/WHEEL
enlil_framework-0.1.1.dist-info/entry_points.txt
enlil_framework-0.1.1.dist-info/top_level.txt
enlil_framework-0.1.1.dist-info/RECORD
