Metadata-Version: 2.4
Name: enlil-framework
Version: 0.1.1
Summary: A real frame built on the shoulders of FastAPI framework. Enlil brings back the beauty of structured, modular design - old-school clarity fused with modern performance.
Home-page: https://github.com/entGriff/enlil
Author: Goga Patarkatsishvili
Project-URL: Source, https://github.com/entGriff/enlil
Project-URL: Bug Reports, https://github.com/entGriff/enlil/issues
Project-URL: Documentation, https://github.com/entGriff/enlil#readme
Requires-Python: >=3.11
Requires-Dist: fastapi<0.116.0,>=0.115.12
Requires-Dist: click<9.0.0,>=8.2.1
Requires-Dist: tortoise-orm<0.26.0,>=0.25.0
Requires-Dist: aerich<0.10.0,>=0.9.0
Requires-Dist: dependency-injector<5.0.0,>=4.46.0
Requires-Dist: jinja2<4.0.0,>=3.1.6
Requires-Dist: pydantic<3.0.0,>=2.11.5
Requires-Dist: pytest<9.0.0,>=8.3.5
Requires-Dist: httpx<0.29.0,>=0.28.1
Requires-Dist: factory-boy<4.0.0,>=3.3.0
Requires-Dist: pytest-asyncio<0.27.0,>=0.26.0
Requires-Dist: tomlkit<0.14.0,>=0.13.2
Requires-Dist: uvicorn[standard]<0.35.0,>=0.34.2
Provides-Extra: dev
Requires-Dist: ruff~=0.11.12; extra == "dev"
Requires-Dist: textual<4.0.0,>=3.2.0; extra == "dev"
Dynamic: author
Dynamic: home-page
Dynamic: project-url
Dynamic: provides-extra
Dynamic: requires-dist
Dynamic: requires-python
Dynamic: summary
